{"status": "OK", "id": 3386, "response": {"destination_addresses": ["Av. Almte Brown 286, Buenos Aires, Argentina", "Av. Cerviño 3356, C1425 CABA, Argentina", "Av. Díaz Vélez 5063, C1405DCF CABA, Argentina", "Dr. Juan Felipe Aranguren 2701, C1406FWY CABA, Argentina", "Gral. Urquiza 608, C1221ADD CABA, Argentina", "Av. Monroe 3544, C1430BKP CABA, Argentina", "Nueva York 3902-3990, Buenos Aires, Argentina", "C1407KQE, Pedro Calderón de la Barca 1541, C1407KQE CABA, Argentina", "Pilar 950, Buenos Aires, Argentina", "Doctor Profesor Pedro Chutro 3321-3499, C1437 CABA, Argentina", "Combatientes de Malvinas 3000, Buenos Aires, Argentina", "Av. Varela 1307, C1406ELA CABA, Argentina"], "origin_addresses": ["Pola 350, C1408HJH CABA, Argentina"], "rows": [{"elements": [{"distance": {"text": "16.2 km", "value": 16203}, "duration": {"text": "23 mins", "value": 1364}, "duration_in_traffic": {"text": "34 mins", "value": 2038}, "status": "OK"}, {"distance": {"text": "24.9 km", "value": 24893}, "duration": {"text": "33 mins", "value": 1983}, "duration_in_traffic": {"text": "1 hour 1 min", "value": 3661}, "status": "OK"}, {"distance": {"text": "9.1 km", "value": 9063}, "duration": {"text": "27 mins", "value": 1634}, "duration_in_traffic": {"text": "35 mins", "value": 2075}, "status": "OK"}, {"distance": {"text": "6.4 km", "value": 6418}, "duration": {"text": "20 mins", "value": 1191}, "duration_in_traffic": {"text": "23 mins", "value": 1382}, "status": "OK"}, {"distance": {"text": "12.7 km", "value": 12726}, "duration": {"text": "23 mins", "value": 1392}, "duration_in_traffic": {"text": "36 mins", "value": 2148}, "status": "OK"}, {"distance": {"text": "12.6 km", "value": 12611}, "duration": {"text": "38 mins", "value": 2306}, "duration_in_traffic": {"text": "44 mins", "value": 2649}, "status": "OK"}, {"distance": {"text": "7.0 km", "value": 7020}, "duration": {"text": "21 mins", "value": 1277}, "duration_in_traffic": {"text": "23 mins", "value": 1358}, "status": "OK"}, {"distance": {"text": "3.0 km", "value": 3015}, "duration": {"text": "10 mins", "value": 623}, "duration_in_traffic": {"text": "11 mins", "value": 677}, "status": "OK"}, {"distance": {"text": "1.2 km", "value": 1245}, "duration": {"text": "4 mins", "value": 234}, "duration_in_traffic": {"text": "4 mins", "value": 241}, "status": "OK"}, {"distance": {"text": "10.8 km", "value": 10763}, "duration": {"text": "23 mins", "value": 1370}, "duration_in_traffic": {"text": "28 mins", "value": 1691}, "status": "OK"}, {"distance": {"text": "9.6 km", "value": 9632}, "duration": {"text": "27 mins", "value": 1625}, "duration_in_traffic": {"text": "33 mins", "value": 1983}, "status": "OK"}, {"distance": {"text": "7.5 km", "value": 7480}, "duration": {"text": "16 mins", "value": 977}, "duration_in_traffic": {"text": "21 mins", "value": 1241}, "status": "OK"}]}], "status": "OK"}}